adafruit_circuitpython_fruitjam-1.7.0.dist-info/licenses/LICENSE
adafruit_fruitjam/__init__.py
adafruit_fruitjam/graphics.py
adafruit_fruitjam/network.py
adafruit_fruitjam/peripherals.py
adafruit_circuitpython_fruitjam-1.7.0.dist-info/METADATA
adafruit_circuitpython_fruitjam-1.7.0.dist-info/WHEEL
adafruit_circuitpython_fruitjam-1.7.0.dist-info/top_level.txt
adafruit_circuitpython_fruitjam-1.7.0.dist-info/RECORD
