Metadata-Version: 2.4
Name: adafruit-circuitpython-fruitjam
Version: 1.7.0
Summary: Helper library for the FruitJam board
Author-email: Adafruit Industries <circuitpython@adafruit.com>
License: MIT
Project-URL: Homepage, https://github.com/adafruit/Adafruit_CircuitPython_FruitJam
Keywords: adafruit,blinka,circuitpython,micropython,fruitjam,hardware,peripherals
Classifier: Intended Audience :: Developers
Classifier: Topic :: Software Development :: Libraries
Classifier: Topic :: Software Development :: Embedded Systems
Classifier: Topic :: System :: Hardware
Classifier: License :: OSI Approved :: MIT License
Classifier: Programming Language :: Python :: 3
License-File: LICENSE
Requires-Dist: Adafruit-Blinka
Requires-Dist: adafruit-circuitpython-busdevice
Requires-Dist: adafruit-circuitpython-tlv320
Requires-Dist: adafruit-circuitpython-neopixel
Requires-Dist: adafruit-circuitpython-portalbase
Requires-Dist: adafruit-circuitpython-esp32spi
Requires-Dist: adafruit-circuitpython-requests
Requires-Dist: adafruit-circuitpython-bitmap-font
Requires-Dist: adafruit-circuitpython-display-text
Requires-Dist: adafruit-circuitpython-sd
Requires-Dist: adafruit-circuitpython-ntp
Requires-Dist: adafruit-circuitpython-connectionmanager
Requires-Dist: adafruit-circuitpython-simplemath
Provides-Extra: optional
Dynamic: license-file
